splinecloud_scipy/__init__.py
splinecloud_scipy/api_client.py
splinecloud_scipy/parametric_spline.py
splinecloud_scipy/piecewise_polynomial.py
splinecloud_scipy-1.2.7.dist-info/licenses/LICENSE
splinecloud_scipy-1.2.7.dist-info/METADATA
splinecloud_scipy-1.2.7.dist-info/WHEEL
splinecloud_scipy-1.2.7.dist-info/top_level.txt
splinecloud_scipy-1.2.7.dist-info/RECORD
