Metadata-Version: 2.4
Name: splinecloud-scipy
Version: 1.2.7
Summary: A SplineCloud client based on SciPy.
Author-email: Vadym Pasko <vadym@splinecloud.com>
License: MIT License
Project-URL: Homepage, https://github.com/nomad-vagabond/splinecloud-scipy
Keywords: splinecloud,spline,BSpline,interpolation,regression,curve fitting
Classifier: License :: OSI Approved :: MIT License
Classifier: Programming Language :: Python
Classifier: Programming Language :: Python :: 3
Requires-Python: >=3.9
License-File: LICENSE
Requires-Dist: numpy
Requires-Dist: scipy
Requires-Dist: requests
Provides-Extra: dev
Requires-Dist: responses; extra == "dev"
Requires-Dist: mypy; extra == "dev"
Provides-Extra: test
Requires-Dist: responses; extra == "test"
Requires-Dist: matplotlib; extra == "test"
Requires-Dist: mypy; extra == "test"
Dynamic: license-file
